sanzan/__init__.py
sanzan/audio.py
sanzan/exceptions.py
sanzan/keygen.py
sanzan/sanzan.py
sanzan/sz.py
sanzan/video.py
sanzan/youtube.py
Sanzan-2.0.5.dist-info/METADATA
Sanzan-2.0.5.dist-info/WHEEL
Sanzan-2.0.5.dist-info/entry_points.txt
Sanzan-2.0.5.dist-info/top_level.txt
Sanzan-2.0.5.dist-info/RECORD
