Metadata-Version: 2.1
Name: Sanzan
Version: 2.0.5
Summary: Video encryption while maintaining playability.
Home-page: UNKNOWN
License: UNKNOWN
Platform: UNKNOWN
Requires-Dist: numpy
Requires-Dist: yt-dlp
Requires-Dist: opencv-python
Requires-Dist: tqdm
Requires-Dist: pydub
Requires-Dist: numba
Requires-Dist: requests
Requires-Dist: ffmpeg-python
Requires-Dist: pyaudio
